VirtualAssistant/__init__.py
VirtualAssistant/audioinout.py
VirtualAssistant/computer.py
VirtualAssistant/errors.py
VirtualAssistant/gettimedate.py
VirtualAssistant/internet.py
VirtualAssistant/others.py
VirtualAssistant/picture.py
VirtualAssistant-0.0.3.dist-info/LICENSE
VirtualAssistant-0.0.3.dist-info/METADATA
VirtualAssistant-0.0.3.dist-info/WHEEL
VirtualAssistant-0.0.3.dist-info/top_level.txt
VirtualAssistant-0.0.3.dist-info/RECORD
