Metadata-Version: 2.1
Name: VirtualAssistant
Version: 0.0.3
Summary: VirtualAssistant is a python package that allows user to make simple Virtual Assistants with already defined commands with only one import.
Home-page: https://github.com/Naman23-coder/VirtualAssistant
Author: Naman Sharma
Author-email: namansharma232009@gmail.com
License: MIT
Platform: UNKNOWN
Requires-Dist: pyttsx3
Requires-Dist: SpeechRecognition
Requires-Dist: colorama
Requires-Dist: pywhatkit
Requires-Dist: requests
